ts_clarity-0.0.5.dist-info/WHEEL
ts_clarity-0.0.5.dist-info/LICENSE
ts_clarity-0.0.5.dist-info/top_level.txt
ts_clarity-0.0.5.dist-info/RECORD
ts_clarity-0.0.5.dist-info/METADATA
tree_sitter_clarity/binding.c
tree_sitter_clarity/py.typed
tree_sitter_clarity/_binding.abi3.so
tree_sitter_clarity/__init__.pyi
tree_sitter_clarity/__init__.py
tree_sitter_clarity/queries/highlights.scm
