Metadata-Version: 2.1
Name: ts-clarity
Version: 0.0.5
Summary: Clarity grammar for tree-sitter
Author-email: Franco Bregante <fbregante9@gmail.com>
License: MIT
Project-URL: Homepage, https://github.com/tree-sitter/tree-sitter-clarity
Keywords: incremental,parsing,tree-sitter,clarity
Classifier: Intended Audience :: Developers
Classifier: License :: OSI Approved :: MIT License
Classifier: Topic :: Software Development :: Compilers
Classifier: Topic :: Text Processing :: Linguistic
Classifier: Typing :: Typed
Requires-Python: >=3.8
License-File: LICENSE
Provides-Extra: core
Requires-Dist: tree-sitter ~=0.21 ; extra == 'core'
